tapi/__init__.py
tapi/api/__init__.py
tapi/api/tenant.py
tapi/api/action/__init__.py
tapi/api/action/actions.py
tapi/api/action/events.py
tapi/api/action/logs.py
tapi/api/admin/__init__.py
tapi/api/admin/action_egress_control_rules.py
tapi/api/admin/admin.py
tapi/api/admin/ip_access_control.py
tapi/api/admin/job.py
tapi/api/admin/scim.py
tapi/api/admin/template.py
tapi/api/admin/user.py
tapi/api/audit_log/__init__.py
tapi/api/audit_log/audit_logs.py
tapi/api/case/__init__.py
tapi/api/case/actions.py
tapi/api/case/activities.py
tapi/api/case/assignees.py
tapi/api/case/blocks.py
tapi/api/case/cases.py
tapi/api/case/comments.py
tapi/api/case/fields.py
tapi/api/case/files.py
tapi/api/case/inputs.py
tapi/api/case/linked_cases.py
tapi/api/case/metadata.py
tapi/api/case/notes.py
tapi/api/case/records.py
tapi/api/case/subscribers.py
tapi/api/credential/__init__.py
tapi/api/credential/credentials.py
tapi/api/event/__init__.py
tapi/api/event/events.py
tapi/api/folder/__init__.py
tapi/api/folder/folders.py
tapi/api/note/__init__.py
tapi/api/note/notes.py
tapi/api/record/__init__.py
tapi/api/record/artifacts.py
tapi/api/record/records.py
tapi/api/record/types.py
tapi/api/report/__init__.py
tapi/api/report/reporting.py
tapi/api/resource/__init__.py
tapi/api/resource/resources.py
tapi/api/story/__init__.py
tapi/api/story/change_requests.py
tapi/api/story/drafts.py
tapi/api/story/groups.py
tapi/api/story/runs.py
tapi/api/story/stories.py
tapi/api/story/versions.py
tapi/api/team/__init__.py
tapi/api/team/members.py
tapi/api/team/teams.py
tapi/client/__init__.py
tapi/client/client.py
tapi/utils/helpers.py
tapi/utils/http.py
tapi/utils/testing_decorators.py
tapi/utils/types.py
tapi_python-0.1.2.dist-info/licenses/LICENSE
tapi_python-0.1.2.dist-info/METADATA
tapi_python-0.1.2.dist-info/WHEEL
tapi_python-0.1.2.dist-info/top_level.txt
tapi_python-0.1.2.dist-info/RECORD
