Metadata-Version: 2.4
Name: tapi-python
Version: 0.1.2
Summary: Tines REST API wrapper
Home-page: https://github.com/1Doomdie1/Tapi
Author: Todoran Horia
License: GPL-3.0
Classifier: License :: OSI Approved :: GNU General Public License v3 (GPLv3)
Classifier: Programming Language :: Python :: 3.10
Classifier: Operating System :: OS Independent
Requires-Python: >=3.10
License-File: LICENSE
Requires-Dist: annotated-types==0.7.0
Requires-Dist: build==1.2.2.post1
Requires-Dist: certifi==2024.12.14
Requires-Dist: charset-normalizer==3.4.1
Requires-Dist: colorama==0.4.6
Requires-Dist: idna==3.10
Requires-Dist: packaging==24.2
Requires-Dist: pydantic==2.10.6
Requires-Dist: pydantic_core==2.27.2
Requires-Dist: pyproject_hooks==1.2.0
Requires-Dist: python-dotenv==1.0.1
Requires-Dist: requests==2.32.3
Requires-Dist: setuptools==75.8.0
Requires-Dist: typing_extensions==4.12.2
Requires-Dist: urllib3==2.3.0
Provides-Extra: dev
Requires-Dist: pytest; extra == "dev"
Requires-Dist: twine; extra == "dev"
Dynamic: author
Dynamic: classifier
Dynamic: description
Dynamic: description-content-type
Dynamic: home-page
Dynamic: license
Dynamic: license-file
Dynamic: provides-extra
Dynamic: requires-dist
Dynamic: requires-python
Dynamic: summary
